marwan/__init__.py
marwan/main.py
marwan-0.1.3.dist-info/LICENSE
marwan-0.1.3.dist-info/METADATA
marwan-0.1.3.dist-info/WHEEL
marwan-0.1.3.dist-info/entry_points.txt
marwan-0.1.3.dist-info/top_level.txt
marwan-0.1.3.dist-info/RECORD
