Metadata-Version: 2.1
Name: marwan
Version: 0.1.3
Summary: Quickly access my important webpages from the command line.
Home-page: https://github.com/marwanhawari/marwan
Author: Marwan Hawari
Author-email: marwan.hawari@gmail.com
License: MIT
Platform: UNKNOWN
Classifier: Programming Language :: Python :: 3
Classifier: License :: OSI Approved :: MIT License
Classifier: Operating System :: OS Independent
Requires-Python: >=3.6
License-File: LICENSE
